MANIFEST.in
README.md
setup.py
driftconfig/VERSION
driftconfig/__init__.py
driftconfig/backends.py
driftconfig/cli.py
driftconfig/config.py
driftconfig/relib.py
driftconfig/schemautil.py
driftconfig/testhelpers.py
driftconfig/util.py
python_driftconfig.egg-info/PKG-INFO
python_driftconfig.egg-info/SOURCES.txt
python_driftconfig.egg-info/dependency_links.txt
python_driftconfig.egg-info/entry_points.txt
python_driftconfig.egg-info/requires.txt
python_driftconfig.egg-info/top_level.txt